src/runner.v
// cd C:\iverilog\runner                   АНДРЕЙ           
// cd C:\iverilog\runner\Lab5-Cxemota      ЮЛЯ
// iverilog -o ./compiled ./src/runner.v ./src/runner_tb.v ./src/runner_lab.v
// vvp ./compiled 
module runner
(
    input miso,                         // линия данных от ведомого устройства (Slave) к мастеру (Master)
    input rstn,                         // cигнал сброса (активный низкий)    rstn = 0 -> reset
    input sys_clk,                      // главный системный тактовый сигнал
    input t_start,                      // сигнал начала работы
    input up,                           // сигнал управления счетчиком светодиодов
    output [5:0] led,                   // светодиоды
    output cs,                          // активный низкий сигнал, указывает на активность передачи
    output mosi,                        // данные, отправляемые от мастера
    output sclk                         // тактовый сигнал, активный во время передачи данных (transact1 и transact2)
);

parameter reg_width = 8;                                // шина регистров (8 бит)
parameter counter_width = $clog2(reg_width);            // определение минимального количества бит, необходимых для представления чисел в диапазоне от 0 до reg_width - 1
parameter reset = 0;                                    // cброс всех сигналов и данных
parameter idle = 1;                                     // ожидание команды запуска (t_start)
parameter load = 2;                                     // подготовка данных для передачи, запись в mosi_d из led
parameter transact1 = 3;                                // передача данных по SPI; чередование состояний для тактирования
parameter transact2 = 4;                                // передача данных по SPI; чередование состояний для тактирования
parameter unload = 5;                                   // завершение передачи, сброс

integer tmpcs = 1;
reg [reg_width-1:0] mosi_d;                // данные, которые будут отправляться через линию MOSI
reg [reg_width-1:0] miso_d;                // данные, получаемые через линию MISO
reg [counter_width:0] count;               // счетчик битов для передачи данных
reg [3:0] state;                           // текущий статус состояния
reg [2:0] led_counter;                     // счетчик, управляющий состоянием светодиодов

initial
    begin
        led_counter <= 0;   
        mosi_d <= 0;
        miso_d <= 0;
        state <= 0;
    end

always @(state)
    begin
        case (state)
          reset:
              begin
                miso_d <= 0;
                mosi_d <= 0;
                count <= 0;
                tmpcs <= 1;
              end
          idle:
              begin
                miso_d <= 0;
                mosi_d <= 0;
                count <= 0;
                tmpcs <= 1;
              end
          load:
              begin
                miso_d <= 0;
                mosi_d <= led;
                count <= reg_width;
                tmpcs <= 0;
              end
          transact1:
              begin
                tmpcs <= 0;
                miso_d <= {miso_d[reg_width-2:0], miso};
                mosi_d <= {mosi_d[reg_width-2:0], 1'b0};
                count <= count-1;
              end
          transact2:
              begin
                tmpcs <= 0;
                miso_d <= {miso_d[reg_width-2:0], miso};
                mosi_d <= {mosi_d[reg_width-2:0], 1'b0};
                count <= count-1;
              end
          unload:
              begin
                miso_d <= 0;
                mosi_d <= 0;
                count <= 0;
                tmpcs <= 1;
              end
          default:
              begin
                miso_d <= 0;
                mosi_d <= 0;
                count <= 0;
                tmpcs <= 1;
              end
       endcase
   end


  always @(posedge sys_clk)
  begin
    if (!rstn)
      state = reset;
    else
      case (state)
        reset:
          if (!t_start)
            state = load;
          else
            state = idle;
        idle:
          if (!t_start)
            state = load;
        load:
          if (count != 0)
            state = transact1;
          else
            state = reset;
        transact1:
          if (count != 0)
            state = transact2;
          else
            state = unload;
        transact2:
          if (count != 0)
            state = transact1;
          else
            state = unload;
        unload:
          if (!t_start)
            state = load;
          else
            state = idle;
      endcase
  end

  assign cs = tmpcs;
  assign mosi = ( ~cs ) ? mosi_d[reg_width-1] : 1'bz;
  assign sclk = ( state == transact1 || state == transact2) ? sys_clk : 1'b0;

always @(posedge sys_clk)
begin
    if (!rstn)
    begin
        led_counter <= 0;
    end
    else
    begin
        if (!up)
            begin
                led_counter <= led_counter + 1;
                if (led_counter == 5)
                    begin
                        led_counter <= 0;
                    end
            end
    end
end

genvar i;
generate
  for (i = 0; i < 6; i = i + 1)
  begin
    assign led[i] = (rstn ? led_counter != i : 0);
  end
endgenerate

endmodule

src/runner_tb.v
`timescale 1ns / 1ps

module runner_tb();

reg rstn;               
reg sys_clk;             
reg t_start;             
reg up;                  
wire [5:0] led;         
wire cs;                
reg miso;               
wire mosi;              
wire sclk;              

runner master (
    .led(led),
    .rstn(rstn),
    .sys_clk(sys_clk),
    .t_start(t_start),
    .up(up),
    .cs(cs),
    .miso(miso),
    .mosi(mosi),
    .sclk(sclk)
);

initial begin
    sys_clk = 0;
    forever #5 sys_clk = ~sys_clk; 
end

initial begin
    rstn = 0;
    t_start = 1;
    up = 1;
    miso = 0; 

    #10;
    rstn = 1; 
    #10;
    up = 0;
    #10; 
    up = 1;

    t_start = 0; 
    #10;
    t_start = 1;

    #100;
    $stop;
end

    initial begin
        $dumpfile("./runner_out.vcd");  
        $dumpvars(0, runner_tb);       
        #1000 $finish;                 
    end

endmodule


//`timescale 1ns / 1ps

//module runner_tb();

//  parameter reg_width = 8;
//  reg rstn;
//  reg sys_clk;
//  reg cs;
//  reg mosi;
//  wire [5:0] led;

//  runner_lab #(
//    .reg_width(reg_width)
//  ) slave(
//    .led(led),
//    .rstn(rstn),
//    .sys_clk(sys_clk),
//    .cs(cs),
//    .mosi(mosi),
//    .sclk() 
//  );
//  
//  reg [7:0] _mosi;

//  initial begin
//    sys_clk = 0;
//    forever #5 sys_clk = ~sys_clk;
//  end

//  initial begin
//    rstn = 0;
//    cs = 1;
//    mosi = 0;

//    #10;
//    rstn = 1;
//    #10;

//    cs = 0; 
//    _mosi = 8'b00101010; 

//      mosi = _mosi[0]; 
//      #5; 
//      mosi = _mosi[1]; 
//      #5; 
//      mosi = _mosi[2]; 
//      #5; 
//      mosi = _mosi[3]; 
//      #5; 
//      mosi = _mosi[4];
//      #5; 
//      mosi = _mosi[5];
//      #5; 
//      mosi = _mosi[6]; 
//      #5; 
//      mosi = _mosi[7]; 
//      #5; 

//    cs = 1;
//    #10;

//    if (led != 6'b101010) 
//      $display("Test failed: led = %b, expected led = 101010", led);
//    else
//      $display("Test passed: led = %b", led);

//    #1000;
//    $finish;
//end

//initial begin
//        $dumpfile("./runner_out.vcd"); 
//        $dumpvars(0, runner_tb);       
//        #1000 $finish;                 
//    end

//endmodule

runner_out.vcd
$date
	Thu Nov 21 19:34:37 2024
$end
$version
	Icarus Verilog
$end
$timescale
	1ps
$end
$scope module runner_tb $end
$var wire 1 ! sclk $end
$var wire 1 " mosi $end
$var wire 6 # led [5:0] $end
$var wire 1 $ cs $end
$var reg 1 % miso $end
$var reg 1 & rstn $end
$var reg 1 ' sys_clk $end
$var reg 1 ( t_start $end
$var reg 1 ) up $end
$scope module master $end
$var wire 1 % miso $end
$var wire 1 & rstn $end
$var wire 1 ' sys_clk $end
$var wire 1 ( t_start $end
$var wire 1 ) up $end
$var wire 1 ! sclk $end
$var wire 1 " mosi $end
$var wire 6 * led [5:0] $end
$var wire 1 $ cs $end
$var parameter 32 + counter_width $end
$var parameter 32 , idle $end
$var parameter 32 - load $end
$var parameter 32 . reg_width $end
$var parameter 32 / reset $end
$var parameter 32 0 transact1 $end
$var parameter 32 1 transact2 $end
$var parameter 32 2 unload $end
$var reg 4 3 count [3:0] $end
$var reg 3 4 led_counter [2:0] $end
$var reg 8 5 miso_d [7:0] $end
$var reg 8 6 mosi_d [7:0] $end
$var reg 4 7 state [3:0] $end
$var integer 32 8 tmpcs [31:0] $end
$scope begin genblk1[0] $end
$var parameter 2 9 i $end
$upscope $end
$scope begin genblk1[1] $end
$var parameter 2 : i $end
$upscope $end
$scope begin genblk1[2] $end
$var parameter 3 ; i $end
$upscope $end
$scope begin genblk1[3] $end
$var parameter 3 < i $end
$upscope $end
$scope begin genblk1[4] $end
$var parameter 4 = i $end
$upscope $end
$scope begin genblk1[5] $end
$var parameter 4 > i $end
$upscope $end
$upscope $end
$upscope $end
$enddefinitions $end
$comment Show the parameter values. $end
$dumpall
b101 >
b100 =
b11 <
b10 ;
b1 :
b0 9
b101 2
b100 1
b11 0
b0 /
b1000 .
b10 -
b1 ,
b11 +
$end
#0
$dumpvars
b1 8
b0 7
b0 6
b0 5
b0 4
b0 3
b0 *
1)
1(
0'
0&
0%
1$
b0 #
z"
0!
$end
#5000
1'
#10000
b111110 #
b111110 *
0'
1&
#15000
b1 7
1'
#20000
0'
0)
#25000
b111101 #
b111101 *
b1 4
1'
#30000
0'
0(
1)
#35000
0"
0$
b0 8
b1000 3
b111101 6
b10 7
1'
#40000
0'
1(
#45000
b111 3
b1111010 6
1!
b11 7
1'
#50000
0!
0'
#55000
1"
b110 3
b11110100 6
b100 7
1!
1'
#60000
0!
0'
#65000
b101 3
b11101000 6
b11 7
1!
1'
#70000
0!
0'
#75000
b100 3
b11010000 6
b100 7
1!
1'
#80000
0!
0'
#85000
b11 3
b10100000 6
b11 7
1!
1'
#90000
0!
0'
#95000
0"
b10 3
b1000000 6
b100 7
1!
1'
#100000
0!
0'
#105000
1"
b1 3
b10000000 6
b11 7
1!
1'
#110000
0!
0'
#115000
0"
b0 3
b0 6
b100 7
1!
1'
#120000
0!
0'
#125000
z"
1$
b1 8
b101 7
0!
1'
#130000
0'
#135000
b1 7
1'
